nepalithar/__init__.py
nepalithar/caste.py
nepalithar/helper.py
nepalithar/data/caste.db
nepalithar-0.0.2.dist-info/LICENSE
nepalithar-0.0.2.dist-info/METADATA
nepalithar-0.0.2.dist-info/WHEEL
nepalithar-0.0.2.dist-info/top_level.txt
nepalithar-0.0.2.dist-info/RECORD
