Metadata-Version: 2.1
Name: nepalithar
Version: 0.0.2
Summary: This package can be used to detect, produce Nepali caste.
Home-page: https://github.com/PublisherName/nepalithar
Author: Subash Ghimire
Author-email: pip@subashghimire.info.np
Project-URL: Bug Tracker, https://github.com/PublisherName/nepalithar/issues
Classifier: Programming Language :: Python :: 3
Classifier: License :: OSI Approved :: MIT License
Classifier: Operating System :: OS Independent
Requires-Python: >=3.6
License-File: LICENSE
